dexofuzzy/__init__.py
dexofuzzy/__main__.py
dexofuzzy/bin/__init__.py
dexofuzzy/bin/fuzzy.dll
dexofuzzy/bin/fuzzy_64.dll
dexofuzzy/cli/__init__.py
dexofuzzy/cli/command.py
dexofuzzy/core/__init__.py
dexofuzzy/core/generator.py
dexofuzzy/core/dex/__init__.py
dexofuzzy/core/dex/extractor.py
dexofuzzy-2.0.0.dist-info/LICENSE
dexofuzzy-2.0.0.dist-info/METADATA
dexofuzzy-2.0.0.dist-info/WHEEL
dexofuzzy-2.0.0.dist-info/entry_points.txt
dexofuzzy-2.0.0.dist-info/top_level.txt
dexofuzzy-2.0.0.dist-info/RECORD
