Metadata-Version: 2.1
Name: dexofuzzy
Version: 2.0.0
Summary: Dexofuzzy: Dalvik EXecutable Opcode Fuzzyhash
Home-page: https://github.com/lee1029ng/Dexofuzzy
Author: Shinho Lee
Author-email: lee1029ng@gmail.com
License: Apache License 2.0
Keywords: Android,Malware,Opcode,Birthmark,Similarity digest hash,N-Gram,M-Partial Matching,Clustering
Classifier: License :: OSI Approved :: Apache Software License
Classifier: Programming Language :: Python :: 3.5
Requires-Python: >=3.5
License-File: LICENSE
Requires-Dist: ssdeep ==3.4 ; platform_system != "Windows"
